{
  "Ajax": [
    "assets/images/descendants/Ajax.png",
    "Ajax Enhanced Cells Blueprint",
    "Ajax Stabilizer Blueprint",
    "Ajax Spiral Catalyst Blueprint",
    "Ajax Code"
  ],
  "Blair": [
    "assets/images/descendants/Blair.png",
    "Blair Enhanced Cells",
    "Blair Stabilizer",
    "Blair Spiral Catalyst",
    "Blair Code"
  ],
  "Bunny": [
    "assets/images/descendants/Bunny.png",
    "Bunny Enhanced Cells",
    "Bunny Stabilizer",
    "Bunny Spiral Catalyst",
    "Bunny Code"
  ],
  "Enzo": [
    "assets/images/descendants/Enzo.png",
    "Enzo Enhanced Cells Blueprint",
    "Enzo Stabilizer Blueprint",
    "Enzo Spiral Catalyst Blueprint",
    "Enzo Code"
  ],
  "Esiemo": [
    "assets/images/descendants/Esiemo.png",
    "Esiemo Enhanced Cells Blueprint",
    "Esiemo Stabilizer Blueprint",
    "Esiemo Spiral Catalyst Blueprint",
    "Esiemo Code"
  ],
  "Freyna": [
    "assets/images/descendants/Freyna.png",
    "Freyna Enhanced Cells",
    "Freyna Stabilizer",
    "Freyna Spiral Catalyst",
    "Freyna Code"
  ],
  "Gley": [
    "assets/images/descendants/Gley.png",
    "Gley Enhanced Cells Blueprint",
    "Gley Stabilizer Blueprint",
    "Gley Spiral Catalyst Blueprint",
    "Gley Code"
  ],
  "Hailey": [
    "assets/images/descendants/Hailey.png",
    "Hailey Enhanced Cells Blueprint",
    "Hailey Stabilizer Blueprint",
    "Hailey Spiral Catalyst Blueprint",
    "Hailey Code"
  ],
  "Jayber": [
    "assets/images/descendants/Jayber.png",
    "Jayber Enhanced Cells Blueprint",
    "Jayber Stabilizer Blueprint",
    "Jayber Spiral Catalyst Blueprint",
    "Jayber Code"
  ],
  "Keelan": [
    "assets/images/descendants/Keelan.png",
    "Keelan Enhanced Cells Blueprint",
    "Keelan Stabilizer Blueprint",
    "Keelan Spiral Catalyst Blueprint",
    "Keelan Code"
  ],
  "Kyle": [
    "assets/images/descendants/Kyle.png",
    "Kyle Enhanced Cells Blueprint",
    "Kyle Stabilizer Blueprint",
    "Kyle Spiral Catalyst Blueprint",
    "Kyle Code"
  ],
  "Lepic": [
    "assets/images/descendants/Lepic.png",
    "Lepic Enhanced Cells Blueprint",
    "Lepic Stabilizer Blueprint",
    "Lepic Spiral Catalyst Blueprint",
    "Lepic Code"
  ],
  "Luna": [
    "assets/images/descendants/Luna.png",
    "Luna Enhanced Cells Blueprint",
    "Luna Stabilizer Blueprint",
    "Luna Spiral Catalyst Blueprint",
    "Luna Code"
  ],
  "Sharen": [
    "assets/images/descendants/Sharen.png",
    "Sharen Enhanced Cells",
    "Sharen Stabilizer",
    "Sharen Spiral Catalyst",
    "Sharen Code"
  ],
  "Ultimate Ajax": [
    "assets/images/descendants/Ultimate Ajax.png",
    "Ultimate Ajax Enhanced Cells Blueprint",
    "Ultimate Ajax Stabilizer Blueprint",
    "Ultimate Ajax Spiral Catalyst Blueprint",
    "Ultimate Ajax Code"
  ],
  "Ultimate Bunny": [
    "assets/images/descendants/Ultimate Bunny.png",
    "Ultimate Bunny Enhanced Cells Blueprint",
    "Ultimate Bunny Stabilizer Blueprint",
    "Ultimate Bunny Spiral Catalyst Blueprint",
    "Ultimate Bunny Code"
  ],
  "Ultimate Freyna": [
    "assets/images/descendants/Ultimate Freyna.png",
    "Ultimate Freyna Enhanced Cells Blueprint",
    "Ultimate Freyna Stabilizer Blueprint",
    "Ultimate Freyna Spiral Catalyst Blueprint",
    "Ultimate Freyna Code"
  ],
  "Ultimate Gley": [
    "assets/images/descendants/Ultimate Gley.png",
    "Ultimate Gley Enhanced Cells Blueprint",
    "Ultimate Gley Stabilizer Blueprint",
    "Ultimate Gley Spiral Catalyst Blueprint",
    "Ultimate Gley Code"
  ],
  "Ultimate Lepic": [
    "assets/images/descendants/Ultimate Lepic.png",
    "Ultimate Lepic Enhanced Cells Blueprint",
    "Ultimate Lepic Stabilizer Blueprint",
    "Ultimate Lepic Spiral Catalyst Blueprint",
    "Ultimate Lepic Code"
  ],
  "Ultimate Sharen": [
    "assets/images/descendants/Ultimate Sharen.png",
    "Ultimate Sharen Enhanced Cells Blueprint",
    "Ultimate Sharen Stabilizer Blueprint",
    "Ultimate Sharen Spiral Catalyst Blueprint",
    "Ultimate Sharen Code"
  ],
  "Ultimate Valby": [
    "assets/images/descendants/Ultimate Valby.png",
    "Ultimate Valby Enhanced Cells Blueprint",
    "Ultimate Valby Stabilizer Blueprint",
    "Ultimate Valby Spiral Catalyst Blueprint",
    "Ultimate Valby Code"
  ],
  "Ultimate Viessa": [
    "assets/images/descendants/Ultimate Viessa.png",
    "Ultimate Viessa Enhanced Cells Blueprint",
    "Ultimate Viessa Stabilizer Blueprint",
    "Ultimate Viessa Spiral Catalyst Blueprint",
    "Ultimate Viessa Code"
  ],
  "Valby": [
    "assets/images/descendants/Valby.png",
    "Valby Enhanced Cells Blueprint",
    "Valby Stabilizer Blueprint",
    "Valby Spiral Catalyst Blueprint",
    "Valby Code"
  ],
  "Viessa": [
    "assets/images/descendants/Viessa.png",
    "Viessa Enhanced Cells Blueprint",
    "Viessa Stabilizer Blueprint",
    "Viessa Spiral Catalyst Blueprint",
    "Viessa Code"
  ],
  "Yujin": [
    "assets/images/descendants/Yujin.png",
    "Yujin Enhanced Cells Blueprint",
    "Yujin Stabilizer Blueprint",
    "Yujin Spiral Catalyst Blueprint",
    "Yujin Code"
  ]
}
